sir_equations/__init__.py
sir_equations/main.py
sir_equations-0.1.1.dist-info/LICENSE
sir_equations-0.1.1.dist-info/METADATA
sir_equations-0.1.1.dist-info/WHEEL
sir_equations-0.1.1.dist-info/top_level.txt
sir_equations-0.1.1.dist-info/RECORD
