Metadata-Version: 2.1
Name: sir-equations
Version: 0.1.1
Summary: Advanced epidemiological model combining SIR dynamics with social-psychological behavior patterns
Author: Sai Ganesh Kolan
Author-email: Sai Ganesh Kolan <vgreddy0128@gmail.com>
Requires-Python: >=3.8
License-File: LICENSE
Requires-Dist: numpy
Requires-Dist: scipy
Requires-Dist: pandas
